pm4pygpu/__init__.py
pm4pygpu/attributes.py
pm4pygpu/basic.py
pm4pygpu/cases_df.py
pm4pygpu/constants.py
pm4pygpu/dfg.py
pm4pygpu/format.py
pm4pygpu/sampling.py
pm4pygpu/start_end_activities.py
pm4pygpu/timestamp.py
pm4pygpu/variants.py
pm4pygpu-0.2.4.dist-info/LICENSE
pm4pygpu-0.2.4.dist-info/METADATA
pm4pygpu-0.2.4.dist-info/WHEEL
pm4pygpu-0.2.4.dist-info/top_level.txt
pm4pygpu-0.2.4.dist-info/RECORD
