Metadata-Version: 2.1
Name: pm4pygpu
Version: 0.2.4
Summary: PM4Py GPU
Home-page: http://www.pm4py.org
Author: PADS
Author-email: alessandro.berti89@gmail.com
License: GPL-3.0
Platform: UNKNOWN
Requires-Dist: pm4py
